{
  "gName": "com.google.android.gms.location.places.PlacesOptions.Builder",
  "interfaces": [],
  "dependencyName": "Site",
  "superClass": "java.lang.Object",
  "methods": [
    {
      "correspondingStatus": "manuallyAdapt",
      "dependencyName": "Site",
      "g": {
        "exceptions": [],
        "modifiers": [],
        "name": "build",
        "paramTypes": [],
        "retType": "com.google.android.gms.location.places.PlacesOptions"
      },
      "text": "This type of API does not support conversion. Modify it based on the manual conversion guide.",
      "hName": "",
      "url": "https://developer.huawei.com/consumer/en/doc/android-sdk-keyword-search-0000001050156630"
    },
    {
      "correspondingStatus": "manuallyAdapt",
      "dependencyName": "Site",
      "g": {
        "exceptions": [],
        "modifiers": [],
        "name": "Builder",
        "paramTypes": [],
        "retType": ""
      },
      "text": "This type of API does not support conversion. Modify it based on the manual conversion guide.",
      "hName": "",
      "url": "https://developer.huawei.com/consumer/en/doc/android-sdk-keyword-search-0000001050156630"
    }
  ],
  "innerClass": true,
  "fields": [],
  "modifiers": [
    "final"
  ],
  "type": "class",
  "hName": "",
  "kitName": "Site",
  "status": "manuallyAdapt"
}