{
  "gName": "com.google.firebase.auth.FacebookAuthProvider",
  "interfaces": [],
  "superClass": "java.lang.Object",
  "methods": [
    {
      "correspondingStatus": "matching",
      "hmsVersion": "",
      "g": {
        "exceptions": [],
        "modifiers": [
          "static"
        ],
        "name": "getCredential",
        "paramTypes": [
          {
            "pos": "0",
            "type": "java.lang.String"
          }
        ],
        "retType": "com.google.firebase.auth.AuthCredential"
      },
      "h": {
        "exceptions": [],
        "modifiers": [
          "static"
        ],
        "name": "credentialWithToken",
        "paramTypes": [
          {
            "pos": "0",
            "type": "java.lang.String"
          }
        ],
        "retType": "com.huawei.agconnect.auth.AGConnectAuthCredential"
      },
      "helpUrl": "",
      "tipsInfo": ""
    }
  ],
  "innerClass": false,
  "fields": [
    {
      "correspondingStatus": "manuallyAdapt",
      "hmsVersion": "",
      "g": {
        "name": "FACEBOOK_SIGN_IN_METHOD",
        "modifiers": [
          "static",
          "final"
        ],
        "type": "java.lang.String",
        "value": "facebook.com"
      },
      "helpUrl": "",
      "tipsInfo": ""
    },
    {
      "correspondingStatus": "dummy",
      "hmsVersion": "",
      "g": {
        "name": "PROVIDER_ID",
        "modifiers": [],
        "type": "java.lang.String",
        "value": "facebook.com"
      },
      "helpUrl": "",
      "tipsInfo": "Only Firebase supports this method. For AGC, retain or delete this method as needed."
    }
  ],
  "modifiers": [],
  "type": "class",
  "hName": "com.huawei.agconnect.auth.FacebookAuthProvider"
}