{
  "gName": "com.google.android.gms.maps.GoogleMap.InfoWindowAdapter",
  "interfaces": [],
  "superClass": "",
  "methods": [
    {
      "correspondingStatus": "matching",
      "hmsVersion": "4.0.0.301",
      "g": {
        "exceptions": [],
        "modifiers": [],
        "name": "getInfoContents",
        "paramTypes": [
          {
            "pos": "0",
            "type": "com.google.android.gms.maps.model.Marker"
          }
        ],
        "retType": "android.view.View"
      },
      "h": {
        "exceptions": [],
        "modifiers": [],
        "name": "getInfoContents",
        "paramTypes": [
          {
            "pos": "0",
            "type": "com.huawei.hms.maps.model.Marker"
          }
        ],
        "retType": "android.view.View"
      },
      "helpUrl": "",
      "tipsInfo": ""
    },
    {
      "correspondingStatus": "matching",
      "hmsVersion": "4.0.0.301",
      "g": {
        "exceptions": [],
        "modifiers": [],
        "name": "getInfoWindow",
        "paramTypes": [
          {
            "pos": "0",
            "type": "com.google.android.gms.maps.model.Marker"
          }
        ],
        "retType": "android.view.View"
      },
      "h": {
        "exceptions": [],
        "modifiers": [],
        "name": "getInfoWindow",
        "paramTypes": [
          {
            "pos": "0",
            "type": "com.huawei.hms.maps.model.Marker"
          }
        ],
        "retType": "android.view.View"
      },
      "helpUrl": "",
      "tipsInfo": ""
    }
  ],
  "innerClass": true,
  "fields": [],
  "modifiers": [],
  "type": "interface",
  "hName": "com.huawei.hms.maps.HuaweiMap.InfoWindowAdapter"
}