{
  "gName": "com.google.android.gms.games.multiplayer.realtime.Room",
  "interfaces": [
    "com.google.android.gms.common.data.Freezable<com.google.android.gms.games.multiplayer.realtime.Room>",
    "com.google.android.gms.games.multiplayer.Participatable",
    "android.os.Parcelable"
  ],
  "superClass": "",
  "methods": [
    {
      "correspondingStatus": "notSupport",
      "hmsVersion": "",
      "g": {
        "exceptions": [],
        "modifiers": [
          "abstract"
        ],
        "name": "getAutoMatchCriteria",
        "paramTypes": [],
        "retType": "android.os.Bundle"
      },
      "helpUrl": "",
      "tipsInfo": "HMS Core does not provide this API. You are advised to delete it."
    },
    {
      "correspondingStatus": "notSupport",
      "hmsVersion": "",
      "g": {
        "exceptions": [],
        "modifiers": [
          "abstract"
        ],
        "name": "getParticipant",
        "paramTypes": [
          {
            "pos": "0",
            "type": "java.lang.String"
          }
        ],
        "retType": "com.google.android.gms.games.multiplayer.Participant"
      },
      "helpUrl": "",
      "tipsInfo": "HMS Core does not provide this API. You are advised to delete it."
    },
    {
      "correspondingStatus": "notSupport",
      "hmsVersion": "",
      "g": {
        "exceptions": [],
        "modifiers": [
          "abstract"
        ],
        "name": "getAutoMatchWaitEstimateSeconds",
        "paramTypes": [],
        "retType": "int"
      },
      "helpUrl": "",
      "tipsInfo": "HMS Core does not provide this API. You are advised to delete it."
    },
    {
      "correspondingStatus": "notSupport",
      "hmsVersion": "",
      "g": {
        "exceptions": [],
        "modifiers": [
          "abstract"
        ],
        "name": "getParticipantStatus",
        "paramTypes": [
          {
            "pos": "0",
            "type": "java.lang.String"
          }
        ],
        "retType": "int"
      },
      "helpUrl": "",
      "tipsInfo": "HMS Core does not provide this API. You are advised to delete it."
    },
    {
      "correspondingStatus": "notSupport",
      "hmsVersion": "",
      "g": {
        "exceptions": [],
        "modifiers": [
          "abstract"
        ],
        "name": "getStatus",
        "paramTypes": [],
        "retType": "int"
      },
      "helpUrl": "",
      "tipsInfo": "HMS Core does not provide this API. You are advised to delete it."
    },
    {
      "correspondingStatus": "notSupport",
      "hmsVersion": "",
      "g": {
        "exceptions": [],
        "modifiers": [
          "abstract"
        ],
        "name": "getVariant",
        "paramTypes": [],
        "retType": "int"
      },
      "helpUrl": "",
      "tipsInfo": "HMS Core does not provide this API. You are advised to delete it."
    },
    {
      "correspondingStatus": "notSupport",
      "hmsVersion": "",
      "g": {
        "exceptions": [],
        "modifiers": [
          "abstract"
        ],
        "name": "getCreatorId",
        "paramTypes": [],
        "retType": "java.lang.String"
      },
      "helpUrl": "",
      "tipsInfo": "HMS Core does not provide this API. You are advised to delete it."
    },
    {
      "correspondingStatus": "notSupport",
      "hmsVersion": "",
      "g": {
        "exceptions": [],
        "modifiers": [
          "abstract"
        ],
        "name": "getDescription",
        "paramTypes": [],
        "retType": "java.lang.String"
      },
      "helpUrl": "",
      "tipsInfo": "HMS Core does not provide this API. You are advised to delete it."
    },
    {
      "correspondingStatus": "notSupport",
      "hmsVersion": "",
      "g": {
        "exceptions": [],
        "modifiers": [
          "abstract"
        ],
        "name": "getParticipantId",
        "paramTypes": [
          {
            "pos": "0",
            "type": "java.lang.String"
          }
        ],
        "retType": "java.lang.String"
      },
      "helpUrl": "",
      "tipsInfo": "HMS Core does not provide this API. You are advised to delete it."
    },
    {
      "correspondingStatus": "notSupport",
      "hmsVersion": "",
      "g": {
        "exceptions": [],
        "modifiers": [
          "abstract"
        ],
        "name": "getRoomId",
        "paramTypes": [],
        "retType": "java.lang.String"
      },
      "helpUrl": "",
      "tipsInfo": "HMS Core does not provide this API. You are advised to delete it."
    },
    {
      "correspondingStatus": "notSupport",
      "hmsVersion": "",
      "g": {
        "exceptions": [],
        "modifiers": [
          "abstract"
        ],
        "name": "getParticipantIds",
        "paramTypes": [],
        "retType": "java.util.ArrayList<java.lang.String>"
      },
      "helpUrl": "",
      "tipsInfo": "HMS Core does not provide this API. You are advised to delete it."
    },
    {
      "correspondingStatus": "notSupport",
      "hmsVersion": "",
      "g": {
        "exceptions": [],
        "modifiers": [
          "abstract"
        ],
        "name": "getCreationTimestamp",
        "paramTypes": [],
        "retType": "long"
      },
      "helpUrl": "",
      "tipsInfo": "HMS Core does not provide this API. You are advised to delete it."
    },
    {
      "correspondingStatus": "notSupport",
      "hmsVersion": "",
      "g": {
        "exceptions": [],
        "modifiers": [
          "abstract"
        ],
        "name": "getDescription",
        "paramTypes": [
          {
            "pos": "0",
            "type": "android.database.CharArrayBuffer"
          }
        ],
        "retType": "void"
      },
      "helpUrl": "",
      "tipsInfo": "HMS Core does not provide this API. You are advised to delete it."
    }
  ],
  "innerClass": false,
  "fields": [
    {
      "correspondingStatus": "notSupport",
      "hmsVersion": "",
      "g": {
        "name": "ROOM_STATUS_ACTIVE",
        "modifiers": [],
        "type": "int",
        "value": "3"
      },
      "helpUrl": "",
      "tipsInfo": "HMS Core does not provide this API. You are advised to delete it."
    },
    {
      "correspondingStatus": "notSupport",
      "hmsVersion": "",
      "g": {
        "name": "ROOM_STATUS_AUTO_MATCHING",
        "modifiers": [],
        "type": "int",
        "value": "1"
      },
      "helpUrl": "",
      "tipsInfo": "HMS Core does not provide this API. You are advised to delete it."
    },
    {
      "correspondingStatus": "notSupport",
      "hmsVersion": "",
      "g": {
        "name": "ROOM_STATUS_CONNECTING",
        "modifiers": [],
        "type": "int",
        "value": "2"
      },
      "helpUrl": "",
      "tipsInfo": "HMS Core does not provide this API. You are advised to delete it."
    },
    {
      "correspondingStatus": "notSupport",
      "hmsVersion": "",
      "g": {
        "name": "ROOM_STATUS_INVITING",
        "modifiers": [],
        "type": "int",
        "value": "0"
      },
      "helpUrl": "",
      "tipsInfo": "HMS Core does not provide this API. You are advised to delete it."
    },
    {
      "correspondingStatus": "notSupport",
      "hmsVersion": "",
      "g": {
        "name": "ROOM_VARIANT_DEFAULT",
        "modifiers": [],
        "type": "int",
        "value": "-1"
      },
      "helpUrl": "",
      "tipsInfo": "HMS Core does not provide this API. You are advised to delete it."
    }
  ],
  "modifiers": [
    "abstract"
  ],
  "type": "interface",
  "hName": ""
}