{
  "gName": "com.google.api.services.drive.Drive.About.Get",
  "interfaces": [],
  "dependencyName": "Drive",
  "superClass": "com.google.api.services.drive.DriveRequest<com.google.api.services.drive.model.About>",
  "methods": [
    {
      "correspondingStatus": "matching",
      "dependencyName": "Drive",
      "g": {
        "exceptions": [],
        "modifiers": [
          "protected"
        ],
        "name": "Get",
        "paramTypes": [],
        "retType": ""
      },
      "h": {
        "exceptions": [],
        "modifiers": [
          "protected"
        ],
        "name": "Get",
        "paramTypes": [],
        "retType": ""
      },
      "text": "Documents to be completed",
      "hName": "com.huawei.cloud.services.drive.Drive.About.Get",
      "url": "https://developer.huawei.com/consumer/en/"
    },
    {
      "correspondingStatus": "notSupport",
      "dependencyName": "Drive",
      "g": {
        "exceptions": [
          "java.io.IOException"
        ],
        "modifiers": [],
        "name": "buildHttpRequestUsingHead",
        "paramTypes": [],
        "retType": "com.google.api.client.http.HttpRequest"
      },
      "text": "This API is not supported. Please modify the coding logic.",
      "hName": "",
      "url": "https://developer.huawei.com/consumer/en/"
    },
    {
      "correspondingStatus": "notSupport",
      "dependencyName": "Drive",
      "g": {
        "exceptions": [
          "java.io.IOException"
        ],
        "modifiers": [],
        "name": "executeUsingHead",
        "paramTypes": [],
        "retType": "com.google.api.client.http.HttpResponse"
      },
      "text": "This API is not supported. Please modify the coding logic.",
      "hName": "",
      "url": "https://developer.huawei.com/consumer/en/"
    },
    {
      "correspondingStatus": "matching",
      "dependencyName": "Drive",
      "g": {
        "exceptions": [],
        "modifiers": [],
        "name": "set",
        "paramTypes": [
          {
            "pos": "0",
            "type": "java.lang.String"
          },
          {
            "pos": "1",
            "type": "java.lang.Object"
          }
        ],
        "retType": "com.google.api.services.drive.Drive.About.Get"
      },
      "h": {
        "exceptions": [],
        "modifiers": [],
        "name": "set",
        "paramTypes": [
          {
            "pos": "0",
            "type": "java.lang.String"
          },
          {
            "pos": "1",
            "type": "java.lang.Object"
          }
        ],
        "retType": "com.huawei.cloud.services.drive.Drive.About.Get"
      },
      "text": "Documents to be completed",
      "hName": "com.huawei.cloud.services.drive.Drive.About.Get",
      "url": "https://developer.huawei.com/consumer/en/"
    },
    {
      "correspondingStatus": "matching",
      "dependencyName": "Drive",
      "g": {
        "exceptions": [],
        "modifiers": [],
        "name": "setAlt",
        "paramTypes": [
          {
            "pos": "0",
            "type": "java.lang.String"
          }
        ],
        "retType": "com.google.api.services.drive.Drive.About.Get"
      },
      "h": {
        "exceptions": [],
        "modifiers": [],
        "name": "setForm",
        "paramTypes": [
          {
            "pos": "0",
            "type": "java.lang.String"
          }
        ],
        "retType": "com.huawei.cloud.services.drive.Drive.About.Get"
      },
      "text": "Documents to be completed",
      "hName": "com.huawei.cloud.services.drive.Drive.About.Get",
      "url": "https://developer.huawei.com/consumer/en/"
    },
    {
      "correspondingStatus": "matching",
      "dependencyName": "Drive",
      "g": {
        "exceptions": [],
        "modifiers": [],
        "name": "setFields",
        "paramTypes": [
          {
            "pos": "0",
            "type": "java.lang.String"
          }
        ],
        "retType": "com.google.api.services.drive.Drive.About.Get"
      },
      "h": {
        "exceptions": [],
        "modifiers": [],
        "name": "setFields",
        "paramTypes": [
          {
            "pos": "0",
            "type": "java.lang.String"
          }
        ],
        "retType": "com.huawei.cloud.services.drive.Drive.About.Get"
      },
      "text": "Documents to be completed",
      "hName": "com.huawei.cloud.services.drive.Drive.About.Get",
      "url": "https://developer.huawei.com/consumer/en/"
    },
    {
      "correspondingStatus": "notSupport",
      "dependencyName": "Drive",
      "g": {
        "exceptions": [],
        "modifiers": [],
        "name": "setKey",
        "paramTypes": [
          {
            "pos": "0",
            "type": "java.lang.String"
          }
        ],
        "retType": "com.google.api.services.drive.Drive.About.Get"
      },
      "text": "This API is not supported. Please modify the coding logic.",
      "hName": "",
      "url": "https://developer.huawei.com/consumer/en/"
    },
    {
      "correspondingStatus": "notSupport",
      "dependencyName": "Drive",
      "g": {
        "exceptions": [],
        "modifiers": [],
        "name": "setOauthToken",
        "paramTypes": [
          {
            "pos": "0",
            "type": "java.lang.String"
          }
        ],
        "retType": "com.google.api.services.drive.Drive.About.Get"
      },
      "text": "This API is not supported. Please modify the coding logic.",
      "hName": "",
      "url": "https://developer.huawei.com/consumer/en/"
    },
    {
      "correspondingStatus": "matching",
      "dependencyName": "Drive",
      "g": {
        "exceptions": [],
        "modifiers": [],
        "name": "setPrettyPrint",
        "paramTypes": [
          {
            "pos": "0",
            "type": "java.lang.Boolean"
          }
        ],
        "retType": "com.google.api.services.drive.Drive.About.Get"
      },
      "h": {
        "exceptions": [],
        "modifiers": [],
        "name": "setPrettyPrint",
        "paramTypes": [
          {
            "pos": "0",
            "type": "java.lang.Boolean"
          }
        ],
        "retType": "com.huawei.cloud.services.drive.Drive.About.Get"
      },
      "text": "Documents to be completed",
      "hName": "com.huawei.cloud.services.drive.Drive.About.Get",
      "url": "https://developer.huawei.com/consumer/en/"
    },
    {
      "correspondingStatus": "matching",
      "dependencyName": "Drive",
      "g": {
        "exceptions": [],
        "modifiers": [],
        "name": "setQuotaUser",
        "paramTypes": [
          {
            "pos": "0",
            "type": "java.lang.String"
          }
        ],
        "retType": "com.google.api.services.drive.Drive.About.Get"
      },
      "h": {
        "exceptions": [],
        "modifiers": [],
        "name": "setQuotaId",
        "paramTypes": [
          {
            "pos": "0",
            "type": "java.lang.String"
          }
        ],
        "retType": "com.huawei.cloud.services.drive.Drive.About.Get"
      },
      "text": "Documents to be completed",
      "hName": "com.huawei.cloud.services.drive.Drive.About.Get",
      "url": "https://developer.huawei.com/consumer/en/"
    },
    {
      "correspondingStatus": "notSupport",
      "dependencyName": "Drive",
      "g": {
        "exceptions": [],
        "modifiers": [],
        "name": "setUserIp",
        "paramTypes": [
          {
            "pos": "0",
            "type": "java.lang.String"
          }
        ],
        "retType": "com.google.api.services.drive.Drive.About.Get"
      },
      "text": "This API is not supported. Please modify the coding logic.",
      "hName": "",
      "url": "https://developer.huawei.com/consumer/en/doc/development/Tools-Guides/drive-conversion-0000001050060174#EN-US_TOPIC_0000001050060174__section720424914238"
    }
  ],
  "innerClass": true,
  "fields": [
    {
      "correspondingStatus": "notSupport",
      "dependencyName": "Drive",
      "g": {
        "name": "USER_AGENT_SUFFIX",
        "modifiers": [
          "static",
          "final"
        ],
        "type": "String",
        "value": "Google-API-Java-Client"
      },
      "text": "This API is not supported. Please modify the coding logic.",
      "hName": "",
      "url": "https://developer.huawei.com/consumer/en/"
    }
  ],
  "modifiers": [],
  "type": "class",
  "hName": "com.huawei.cloud.services.drive.Drive.About.Get",
  "kitName": "Drive",
  "status": "notSupport"
}