{
  "gName": "com.google.android.gms.ads.rewarded.RewardedAdLoadCallback",
  "interfaces": [],
  "superClass": "java.lang.Object",
  "methods": [
    {
      "correspondingStatus": "matching",
      "hmsVersion": "",
      "g": {
        "exceptions": [],
        "modifiers": [],
        "name": "onRewardedAdFailedToLoad",
        "paramTypes": [
          {
            "pos": "0",
            "type": "int"
          }
        ],
        "retType": "void"
      },
      "h": {
        "exceptions": [],
        "modifiers": [],
        "name": "onRewardAdFailedToLoad",
        "paramTypes": [
          {
            "pos": "0",
            "type": "int"
          }
        ],
        "retType": "void"
      },
      "helpUrl": "",
      "tipsInfo": ""
    },
    {
      "correspondingStatus": "matching",
      "hmsVersion": "",
      "g": {
        "exceptions": [],
        "modifiers": [],
        "name": "onRewardedAdLoaded",
        "paramTypes": [],
        "retType": "void"
      },
      "h": {
        "exceptions": [],
        "modifiers": [],
        "name": "onRewardedLoaded",
        "paramTypes": [],
        "retType": "void"
      },
      "helpUrl": "",
      "tipsInfo": ""
    },
    {
      "correspondingStatus": "matching",
      "hmsVersion": "",
      "g": {
        "exceptions": [],
        "modifiers": [],
        "name": "RewardedAdLoadCallback",
        "paramTypes": [],
        "retType": ""
      },
      "h": {
        "exceptions": [],
        "modifiers": [],
        "name": "RewardAdLoadListener",
        "paramTypes": [],
        "retType": ""
      },
      "helpUrl": "",
      "tipsInfo": ""
    }
  ],
  "innerClass": false,
  "fields": [],
  "modifiers": [],
  "type": "class",
  "hName": "com.huawei.hms.ads.reward.RewardAdLoadListener"
}