{
  "gName": "com.google.android.gms.games.PlayerLevelInfo",
  "interfaces": [
    "android.os.Parcelable"
  ],
  "superClass": "",
  "methods": [
    {
      "correspondingStatus": "notSupport",
      "hmsVersion": "HMS 4.0.0.300",
      "g": {
        "exceptions": [],
        "modifiers": [
          "final"
        ],
        "name": "equals",
        "paramTypes": [
          {
            "pos": "0",
            "type": "java.lang.Object"
          }
        ],
        "retType": "boolean"
      },
      "helpUrl": "",
      "tipsInfo": "HMS Core does not provide this API. You are advised to delete it."
    },
    {
      "correspondingStatus": "notSupport",
      "hmsVersion": "HMS 4.0.0.300",
      "g": {
        "exceptions": [],
        "modifiers": [
          "final"
        ],
        "name": "isMaxLevel",
        "paramTypes": [],
        "retType": "boolean"
      },
      "helpUrl": "",
      "tipsInfo": "HMS Core does not provide this API. You can ignore it."
    },
    {
      "correspondingStatus": "notSupport",
      "hmsVersion": "HMS 4.0.0.300",
      "g": {
        "exceptions": [],
        "modifiers": [
          "final"
        ],
        "name": "getCurrentLevel",
        "paramTypes": [],
        "retType": "com.google.android.gms.games.PlayerLevel"
      },
      "helpUrl": "",
      "tipsInfo": "HMS Core does not provide this API. You can ignore it."
    },
    {
      "correspondingStatus": "notSupport",
      "hmsVersion": "HMS 4.0.0.300",
      "g": {
        "exceptions": [],
        "modifiers": [
          "final"
        ],
        "name": "getNextLevel",
        "paramTypes": [],
        "retType": "com.google.android.gms.games.PlayerLevel"
      },
      "helpUrl": "",
      "tipsInfo": "HMS Core does not provide this API. You can ignore it."
    },
    {
      "correspondingStatus": "notSupport",
      "hmsVersion": "HMS 4.0.0.300",
      "g": {
        "exceptions": [],
        "modifiers": [
          "final"
        ],
        "name": "hashCode",
        "paramTypes": [],
        "retType": "int"
      },
      "helpUrl": "",
      "tipsInfo": "HMS Core does not provide this API. You are advised to delete it."
    },
    {
      "correspondingStatus": "notSupport",
      "hmsVersion": "HMS 4.0.0.300",
      "g": {
        "exceptions": [],
        "modifiers": [
          "final"
        ],
        "name": "getCurrentXpTotal",
        "paramTypes": [],
        "retType": "long"
      },
      "helpUrl": "",
      "tipsInfo": "HMS Core does not provide this API. You can ignore it."
    },
    {
      "correspondingStatus": "notSupport",
      "hmsVersion": "HMS 4.0.0.300",
      "g": {
        "exceptions": [],
        "modifiers": [
          "final"
        ],
        "name": "getLastLevelUpTimestamp",
        "paramTypes": [],
        "retType": "long"
      },
      "helpUrl": "",
      "tipsInfo": "HMS Core does not provide this API. You can ignore it."
    },
    {
      "correspondingStatus": "notSupport",
      "hmsVersion": "HMS 4.0.0.300",
      "g": {
        "exceptions": [],
        "modifiers": [
          "final"
        ],
        "name": "writeToParcel",
        "paramTypes": [
          {
            "pos": "0",
            "type": "android.os.Parcel"
          },
          {
            "pos": "1",
            "type": "int"
          }
        ],
        "retType": "void"
      },
      "helpUrl": "",
      "tipsInfo": "HMS Core does not provide this API. You are advised to delete it."
    }
  ],
  "innerClass": false,
  "fields": [
    {
      "correspondingStatus": "notSupport",
      "hmsVersion": "HMS 4.0.0.300",
      "g": {
        "name": "CREATOR",
        "modifiers": [
          "static",
          "final"
        ],
        "type": "android.os.Parcelable.Creator<com.google.android.gms.games.PlayerLevelInfo>",
        "value": ""
      },
      "helpUrl": "",
      "tipsInfo": "HMS Core does not provide this API. You are advised to delete it."
    }
  ],
  "modifiers": [
    "final"
  ],
  "type": "class",
  "hName": ""
}