{
  "gName": "com.google.android.gms.fido.fido2.api.common.AttestationConveyancePreference.UnsupportedAttestationConveyancePreferenceException",
  "interfaces": [],
  "superClass": "java.lang.Exception",
  "methods": [
    {
      "correspondingStatus": "notSupport",
      "hmsVersion": "",
      "g": {
        "exceptions": [],
        "modifiers": [],
        "name": "UnsupportedAttestationConveyancePreferenceException",
        "paramTypes": [
          {
            "pos": "0",
            "type": "java.lang.String"
          }
        ],
        "retType": ""
      },
      "helpUrl": "",
      "tipsInfo": "HMS Core does not provide this method in this version. Use the Google API if necessary."
    }
  ],
  "innerClass": true,
  "fields": [],
  "modifiers": [
    "static"
  ],
  "type": "class",
  "hName": ""
}